[
  {
    "id": "matcha",
    "name": "Matcha",
    "jp": "抹茶",
    "tagline": "Stone-ground ceremonial",
    "description": "Single-origin Uji leaves, stone-milled at dawn. A vegetal hush of umami, finished with cold oat cream.",
    "price": "¥820",
    "image": "matcha",
    "glow": "rgba(120, 200, 110, 0.55)",
    "bgFrom": "#0d2418",
    "bgTo": "#1f4a2c",
    "accent": "#9ee8a4"
  },
  {
    "id": "yuzu",
    "name": "Yuzu",
    "jp": "柚子",
    "tagline": "Sun-kissed citrus",
    "description": "Hand-zested Kōchi yuzu, sparkling spring water, a whisper of honey. Bright, electric, alive.",
    "price": "¥780",
    "image": "yuzu",
    "glow": "rgba(255, 210, 90, 0.55)",
    "bgFrom": "#2a2410",
    "bgTo": "#5a4a18",
    "accent": "#ffe080"
  },
  {
    "id": "sakura",
    "name": "Sakura",
    "jp": "桜",
    "tagline": "Blossom infusion",
    "description": "Salt-cured Yoshino petals steeped in spring milk. Floral, faintly almond, undeniably spring.",
    "price": "¥860",
    "image": "sakura",
    "glow": "rgba(255, 170, 200, 0.55)",
    "bgFrom": "#2a1620",
    "bgTo": "#5a2840",
    "accent": "#ffc0d6"
  },
  {
    "id": "hojicha",
    "name": "Hojicha",
    "jp": "焙じ茶",
    "tagline": "Roasted amber",
    "description": "Charcoal-roasted Kyoto leaves. Toasted hazelnut, caramelized sugar, the warmth of a kettle at dusk.",
    "price": "¥740",
    "image": "hojicha",
    "glow": "rgba(230, 140, 70, 0.55)",
    "bgFrom": "#2a1a10",
    "bgTo": "#5a2e16",
    "accent": "#ffba80"
  },
  {
    "id": "ube",
    "name": "Ube",
    "jp": "紫芋",
    "tagline": "Velvet root",
    "description": "Purple yam slow-steamed with coconut cream. Earthy, silken, with a quiet vanilla finish.",
    "price": "¥880",
    "image": "ube",
    "glow": "rgba(180, 120, 255, 0.55)",
    "bgFrom": "#1c1030",
    "bgTo": "#3a1c5c",
    "accent": "#d8b4ff"
  }
]
